django_autotyping/__init__.py
django_autotyping/_compat.py
django_autotyping/app_settings.py
django_autotyping/apps.py
django_autotyping/py.typed
django_autotyping/typing.py
django_autotyping/codemodding/__init__.py
django_autotyping/codemodding/django_context.py
django_autotyping/codemodding/main.py
django_autotyping/codemodding/models.py
django_autotyping/codemodding/codemods/__init__.py
django_autotyping/codemodding/codemods/base.py
django_autotyping/codemodding/codemods/forward_relation_typing_codemod.py
django_autotyping/codemodding/vendoring/__init__.py
django_autotyping/codemodding/vendoring/monkeytype/__init__.py
django_autotyping/codemodding/vendoring/monkeytype/type_checking_imports_transformer.py
django_autotyping/management/__init__.py
django_autotyping/management/commands/__init__.py
django_autotyping/management/commands/_utils.py
django_autotyping/management/commands/add_type_hints.py
django_autotyping/management/commands/generate_stubs.py
django_autotyping/stubbing/__init__.py
django_autotyping/stubbing/codemods/__init__.py
django_autotyping/stubbing/codemods/_global_settings_types.py
django_autotyping/stubbing/codemods/_model_creation.py
django_autotyping/stubbing/codemods/_utils.py
django_autotyping/stubbing/codemods/auth_functions_codemod.py
django_autotyping/stubbing/codemods/base.py
django_autotyping/stubbing/codemods/call_command_codemod.py
django_autotyping/stubbing/codemods/constants.py
django_autotyping/stubbing/codemods/create_overload_codemod.py
django_autotyping/stubbing/codemods/forward_relation_overload_codemod.py
django_autotyping/stubbing/codemods/get_model_overload_codemod.py
django_autotyping/stubbing/codemods/model_init_overload_codemod.py
django_autotyping/stubbing/codemods/query_lookups_overload_codemod.py
django_autotyping/stubbing/codemods/reverse_overload_codemod.py
django_autotyping/stubbing/codemods/settings_codemod.py
django_autotyping/stubbing/codemods/template_loading_codemod.py
django_autotyping-0.5.1.dist-info/LICENSE
django_autotyping-0.5.1.dist-info/METADATA
django_autotyping-0.5.1.dist-info/WHEEL
django_autotyping-0.5.1.dist-info/top_level.txt
django_autotyping-0.5.1.dist-info/RECORD
