Metadata-Version: 2.1
Name: django-autotyping
Version: 0.5.1
Summary: Automatically add type hints for Django powered applications.
Author-email: Viicos <65306057+Viicos@users.noreply.github.com>
License: MIT License
Project-URL: Homepage, https://github.com/Viicos/django-autotyping
Project-URL: Source, https://github.com/Viicos/django-autotyping
Project-URL: Changelog, https://github.com/Viicos/django-autotyping/blob/main/CHANGELOG.md
Project-URL: Documentation, https://viicos.github.io/django-autotyping/
Classifier: Development Status :: 4 - Beta
Classifier: Operating System :: OS Independent
Classifier: Programming Language :: Python :: 3
Classifier: Programming Language :: Python :: 3 :: Only
Classifier: Programming Language :: Python :: 3.8
Classifier: Programming Language :: Python :: 3.9
Classifier: Programming Language :: Python :: 3.10
Classifier: Programming Language :: Python :: 3.11
Classifier: Programming Language :: Python :: 3.12
Classifier: Framework :: Django
Classifier: Typing :: Typed
Classifier: License :: OSI Approved :: MIT License
Classifier: Intended Audience :: Developers
Classifier: Topic :: Software Development :: Libraries :: Python Modules
Classifier: Topic :: Software Development :: Quality Assurance
Requires-Python: >=3.8
License-File: LICENSE
Requires-Dist: django
Requires-Dist: libcst >=0.4.10
Requires-Dist: typing-extensions >=4.4.0 ; python_version < "3.12"
